[
   {
      "model":"employee.employee",
      "pk":1,
      "fields":{
         "name":"Peter",
         "employment_date":"2021-03-28",
         "position":"СЕО",
         "chief":null,
         "salary":3000.0,
         "paid_salary":0.0,
         "level":4
      }
   },
   {
      "model":"employee.employee",
      "pk":2,
      "fields":{
         "name":"Olga",
         "employment_date":"2021-04-09",
         "position":"JR",
         "chief":2,
         "salary":400.0,
         "paid_salary":0.0,
         "level":0
      }
   },
   {
      "model":"employee.employee",
      "pk":3,
      "fields":{
         "name":"Igor",
         "employment_date":"2021-03-28",
         "position":"MD",
         "chief":2,
         "salary":1000.0,
         "paid_salary":0.0,
         "level":1
      }
   },
   {
      "model":"employee.employee",
      "pk":4,
      "fields":{
         "name":"Kolya",
         "employment_date":"2021-04-25",
         "position":"JR",
         "chief":2,
         "salary":400.0,
         "paid_salary":0.0,
         "level":0
      }
   },
   {
      "model":"employee.employee",
      "pk":5,
      "fields":{
         "name":"Pasha",
         "employment_date":"2021-04-25",
         "position":"JR",
         "chief":2,
         "salary":500.0,
         "paid_salary":0.0,
         "level":0
      }
   },
   {
      "model":"employee.employee",
      "pk":6,
      "fields":{
         "name":"Kostya",
         "employment_date":"2021-04-25",
         "position":"JR",
         "chief":2,
         "salary":400.0,
         "paid_salary":0.0,
         "level":0
      }
   },
   {
      "model":"employee.employee",
      "pk":7,
      "fields":{
         "name":"Kate",
         "employment_date":"2021-04-25",
         "position":"JR",
         "chief":2,
         "salary":400.0,
         "paid_salary":0.0,
         "level":0
      }
   },
   {
      "model":"employee.employee",
      "pk":8,
      "fields":{
         "name":"Lena",
         "employment_date":"2021-04-25",
         "position":"SR",
         "chief":2,
         "salary":4500.0,
         "paid_salary":0.0,
         "level":3
      }
   },
   {
      "model":"employee.employee",
      "pk":9,
      "fields":{
         "name":"Natasha",
         "employment_date":"2021-04-25",
         "position":"SR",
         "chief":2,
         "salary":4000.0,
         "paid_salary":0.0,
         "level":0
      }
   },
   {
      "model":"employee.employee",
      "pk":10,
      "fields":{
         "name":"Vlad",
         "employment_date":"2021-04-25",
         "position":"JR",
         "chief":2,
         "salary":1200.0,
         "paid_salary":0.0,
         "level":0
      }
   },
   {
      "model":"employee.employee",
      "pk":11,
      "fields":{
         "name":"Dasha",
         "employment_date":"2021-04-25",
         "position":"JR",
         "chief":2,
         "salary":1100.0,
         "paid_salary":0.0,
         "level":0
      }
   },
   {
      "model":"employee.employee",
      "pk":12,
      "fields":{
         "name":"Sergei",
         "employment_date":"2021-04-25",
         "position":"JR",
         "chief":2,
         "salary":1400.0,
         "paid_salary":0.0,
         "level":0
      }
   }
]